networking_onos-1.0.0.data/data/etc/neutron/plugins/ml2/conf_onos.ini
networking_onos/__init__.py
networking_onos/plugins/__init__.py
networking_onos/plugins/ml2/README
networking_onos/plugins/ml2/driver.py
networking_onos/plugins/ml2/__init__.py
networking_onos/plugins/l3/router.py
networking_onos/plugins/l3/floating_ip.py
networking_onos/plugins/l3/README
networking_onos/plugins/l3/driver.py
networking_onos/plugins/l3/__init__.py
networking_onos/tests/__init__.py
networking_onos/tests/unit/__init__.py
networking_onos/tests/unit/plugins/__init__.py
networking_onos/tests/unit/plugins/ml2/test_driver.py
networking_onos/tests/unit/plugins/ml2/__init__.py
networking_onos/tests/unit/plugins/l3/test_driver.py
networking_onos/tests/unit/plugins/l3/__init__.py
networking_onos/common/__init__.py
networking_onos/common/config.py
networking_onos/common/utils.py
networking_onos-1.0.0.dist-info/dependency_links.txt
networking_onos-1.0.0.dist-info/METADATA
networking_onos-1.0.0.dist-info/WHEEL
networking_onos-1.0.0.dist-info/entry_points.txt
networking_onos-1.0.0.dist-info/metadata.json
networking_onos-1.0.0.dist-info/RECORD
networking_onos-1.0.0.dist-info/top_level.txt
networking_onos-1.0.0.dist-info/DESCRIPTION.rst
networking_onos-1.0.0.dist-info/pbr.json
